input_output/__init__.py
input_output/file_handler.py
input_output/parallel.py
memory/__init__.py
memory/optimization.py
preprocessing/__init__.py
preprocessing/cleaning.py
preprocessing/preprocess.py
training/__init__.py
training/evaluation.py
training/split.py
visualization/__init__.py
visualization/plots.py
esseppi-0.4.3.dist-info/LICENSE
esseppi-0.4.3.dist-info/METADATA
esseppi-0.4.3.dist-info/WHEEL
esseppi-0.4.3.dist-info/top_level.txt
esseppi-0.4.3.dist-info/RECORD
