Metadata-Version: 2.1
Name: esseppi
Version: 0.4.3
Summary: A shared utilities library for data processing, analysis, and interpretation.
Author: Esseppi Zeta
Author-email: Esseppi Zeta <lozingaro@duck.com>
Project-URL: homepage, https://github.com/lozingaro/esseppi
Classifier: Programming Language :: Python :: 3
Classifier: License :: OSI Approved :: MIT License
Classifier: Operating System :: OS Independent
Requires-Python: >=3.7
License-File: LICENSE
Requires-Dist: numpy
Requires-Dist: pandas
Requires-Dist: matplotlib
Requires-Dist: psutil
Requires-Dist: logging
Requires-Dist: joblib
